AUTHORS.rst
CHANGELOG.rst
LICENSE.txt
MANIFEST.in
README.md
setup.cfg
setup.py
django_inline_wrestler/__init__.py
django_inline_wrestler/admin.py
django_inline_wrestler.egg-info/PKG-INFO
django_inline_wrestler.egg-info/SOURCES.txt
django_inline_wrestler.egg-info/dependency_links.txt
django_inline_wrestler.egg-info/top_level.txt
django_inline_wrestler/static/django_inline_wrestler/css/django-inline-wrestler.css
django_inline_wrestler/static/django_inline_wrestler/js/django-inline-wrestler.js