Metadata-Version: 1.1
Name: django-inline-wrestler
Version: 4.6
Summary: Wrestle your django inlines with jQuery and Grappelli.
Home-page: https://github.com/ninapavlich/django-inline-wrestler
Author: Nina Pavlich
Author-email: nina@ninalp.com
License: BSD
Platform: UNKNOWN
Classifier: Development Status :: 4 - Beta
Classifier: Environment :: Web Environment
Classifier: Framework :: Django
Classifier: Intended Audience :: Developers
Classifier: License :: OSI Approved
Classifier: Operating System :: OS Independent
Classifier: Programming Language :: Python
